SrpnetApi/__init__.py
SrpnetApi/accounts.py
SrpnetApi/autopay.py
SrpnetApi/client.py
SrpnetApi/documents.py
SrpnetApi/other.py
SrpnetApi/outages.py
SrpnetApi/payments.py
SrpnetApi/usage.py
srpnet_api-2025.10.dist-info/METADATA
srpnet_api-2025.10.dist-info/WHEEL
srpnet_api-2025.10.dist-info/licenses/LICENSE
srpnet_api-2025.10.dist-info/RECORD
