Metadata-Version: 2.4
Name: SRPNET_api
Version: 2025.10
Summary: An unofficial, mostly complete, python abstraction of the SRPNET api
Project-URL: Homepage, https://github.com/Spencer-Sawyer/SRPNET-api
Project-URL: Issues, https://github.com/Spencer-Sawyer/SRPNET-api/issues
Author-email: Spencer Sawyer <spencer@spencersawyer.com>
License-Expression: MIT
License-File: LICENSE
Classifier: Operating System :: OS Independent
Classifier: Programming Language :: Python :: 3
Requires-Python: >=3.10
Requires-Dist: datetime
Requires-Dist: requests
